dist_gcs_pdf_processing/__init__.py
dist_gcs_pdf_processing/__main__.py
dist_gcs_pdf_processing/config.py
dist_gcs_pdf_processing/drive_utils_oauth2.py
dist_gcs_pdf_processing/env.py
dist_gcs_pdf_processing/gcs_utils.py
dist_gcs_pdf_processing/main.py
dist_gcs_pdf_processing/ocr.py
dist_gcs_pdf_processing/shared.py
dist_gcs_pdf_processing/storage_interface.py
dist_gcs_pdf_processing/unified_worker.py
dist_gcs_pdf_processing-2.0.0.dist-info/licenses/LICENSE
dist_gcs_pdf_processing-2.0.0.dist-info/METADATA
dist_gcs_pdf_processing-2.0.0.dist-info/WHEEL
dist_gcs_pdf_processing-2.0.0.dist-info/entry_points.txt
dist_gcs_pdf_processing-2.0.0.dist-info/top_level.txt
dist_gcs_pdf_processing-2.0.0.dist-info/RECORD
