Metadata-Version: 2.4
Name: dist-gcs-pdf-processing
Version: 2.0.0
Summary: Unified PDF processing pipeline with resume capability, multi-storage backends (GCS/Drive), distributed locking, and production-ready deployment.
Home-page: https://github.com/youruser/dist-gcs-pdf-processing
Author: Pulkit Kumar
Author-email: Pulkit Kumar <your@email.com>
License: MIT License
Project-URL: Homepage, https://github.com/youruser/dist-gcs-pdf-processing
Project-URL: Source, https://github.com/youruser/dist-gcs-pdf-processing
Project-URL: Tracker, https://github.com/youruser/dist-gcs-pdf-processing/issues
Classifier: Programming Language :: Python :: 3
Classifier: License :: OSI Approved :: MIT License
Classifier: Operating System :: OS Independent
Classifier: Development Status :: 4 - Beta
Classifier: Intended Audience :: Developers
Classifier: Topic :: Software Development :: Libraries :: Application Frameworks
Requires-Python: >=3.9
License-File: LICENSE
Requires-Dist: fastapi
Requires-Dist: uvicorn
Requires-Dist: google-cloud-storage
Requires-Dist: requests
Requires-Dist: python-dotenv
Requires-Dist: pypdf
Requires-Dist: markdown2
Requires-Dist: weasyprint
Requires-Dist: python-docx
Requires-Dist: redis
Requires-Dist: prometheus_client
Dynamic: author
Dynamic: home-page
Dynamic: license-file
Dynamic: requires-python
